src/__init__.py
src/agent.py
src/config/__init__.py
src/config/env.py
src/config/prompts.py
src/tools/__init__.py
src/tools/mongo_stock.py
src/tools/vector_search.py
src/tools/yfinance.py
src/utils/__init__.py
src/utils/llm.py
llmfa_agent-0.1.0.dist-info/METADATA
llmfa_agent-0.1.0.dist-info/WHEEL
llmfa_agent-0.1.0.dist-info/RECORD
