Metadata-Version: 2.4
Name: llmfa-agent
Version: 0.1.0
Summary: Financial Data Assistant - A PocketFlow-based LLM library for financial data chat with tool calling
Project-URL: Homepage, https://github.com/llmfa/llmfa-agent
Project-URL: Documentation, https://github.com/llmfa/llmfa-agent#readme
Author: LLMFA Team
License: MIT
Keywords: agent,ai,assistant,chatbot,financial,gemini,llm,pocketflow
Classifier: Development Status :: 3 - Alpha
Classifier: Intended Audience :: Developers
Classifier: License :: OSI Approved :: MIT License
Classifier: Programming Language :: Python :: 3
Classifier: Programming Language :: Python :: 3.12
Classifier: Topic :: Scientific/Engineering :: Artificial Intelligence
Requires-Python: >=3.12
Requires-Dist: google-genai>=1.33.0
Requires-Dist: google-generativeai
Requires-Dist: pocketflow
Requires-Dist: pymongo[srv]
Requires-Dist: python-dateutil
Requires-Dist: python-dotenv>=1.1.1
Requires-Dist: yfinance>=0.2.65
Provides-Extra: dev
Requires-Dist: ipykernel>=6.30.1; extra == 'dev'
Requires-Dist: pytest; extra == 'dev'
Requires-Dist: pytest-asyncio; extra == 'dev'
